{
    "DNDConfig": null,
    "_height_": {
        "type": "string",
        "value": "86%"
    },
    "_margin_": [
        0,
        0,
        0,
        0
    ],
    "_orientation_": 6,
    "_padding_": [
        0,
        0,
        0,
        0
    ],
    "_percent_": true,
    "_skin_": "s5ad458ecf2642d4b88e18161a060fd7",
    "_top_": {
        "type": "string",
        "value": "0%"
    },
    "_width_": {
        "type": "string",
        "value": "90%"
    },
    "allboxes": [],
    "allowhorizontalbounce": false,
    "allowverticalbounce": true,
    "bounces": true,
    "canUpdateUI": true,
    "centerx": {
        "type": "string",
        "value": "46%"
    },
    "children": [
        "flxGroupContent",
        "navFooterBarPostLogin"
    ],
    "clipbounds": true,
    "containerweight": 100,
    "decelerat": false,
    "dragg": false,
    "enablescrolling": true,
    "horizontalscrollindicator": true,
    "id": "flxContainerForm",
    "info": null,
    "iscustomlayout": false,
    "isvisible": true,
    "kuid": "j2118a0f7ca14b56960d8bb91583eb2e",
    "layouttype": 4,
    "name": "kony.ui.FlexScrollContainer",
    "pagingenabled": false,
    "parent": "flxMainContainer",
    "pf": "frmWithdrawHearingStep3",
    "responsiveData": {
        "b1": {
            "centerX": {
                "type": "string",
                "value": "50%"
            },
            "height": {
                "type": "string",
                "value": "81%"
            },
            "width": {
                "type": "string",
                "value": "100%"
            }
        },
        "b3": {
            "centerX": {
                "type": "string",
                "value": "50%"
            },
            "height": {
                "type": "string",
                "value": "72%"
            },
            "width": {
                "type": "string",
                "value": "100%"
            }
        }
    },
    "retaincontentalignment": false,
    "retainflexpositionproperties": false,
    "scrolldirection": 2,
    "snapgridsize": 10,
    "snaptogrid": true,
    "track": false,
    "verticalscrollindicator": true,
    "vizProps": {},
    "wType": "FlexScrollContainer",
    "widgetalignment": 1,
    "zindex": 1
}