{
    "@class": "com.kony.gen.viz.model.component.KVizUserWidget",
    "DNDConfig": null,
    "_children_": [],
    "_height_": {
        "type": "string",
        "value": "100%"
    },
    "_left_": {
        "type": "string",
        "value": "0dp"
    },
    "_margin_": [
        0,
        0,
        0,
        0
    ],
    "_orientation_": 1,
    "_padding_": [
        0,
        0,
        0,
        0
    ],
    "_percent_": true,
    "_skin_": "s47016e6eec84bb2a673e11067a07bdf",
    "_top_": {
        "type": "string",
        "value": "40px"
    },
    "_width_": {
        "type": "string",
        "value": "100%"
    },
    "android": {},
    "androidwearos": {},
    "areflexpropsreferenced": false,
    "canUpdateUI": true,
    "clipbounds": true,
    "containerweight": 0,
    "dataDiffs": {
        "flxProfileMenuContainer": {
            "__events__": {},
            "__info__": {
                "kuid": "e576d0a26aca4658a700927df7c8a90e",
                "srcKUID": "gc1f460cc52d40b7a09f3f5819ed15e1",
                "wType": "FlexContainer"
            },
            "responsiveData": {
                "b1": {
                    "isVisible": false
                },
                "b3": {
                    "isVisible": true
                }
            }
        },
        "flxProfileMenuHeading": {
            "__events__": {},
            "__info__": {
                "kuid": "ad8649cc55444f18848fb3bf54c5bec3",
                "srcKUID": "b784de5d5f634d38a51c1b0baf0294cd",
                "wType": "FlexContainer"
            }
        },
        "flxProfileMenuOptions": {
            "__events__": {},
            "__info__": {
                "kuid": "d1312509e289449b919b1522ff52e622",
                "srcKUID": "b89f97b14c184597b6ade5c73b7f982c",
                "wType": "FlexContainer"
            }
        },
        "lblProfileHeading": {
            "__events__": {},
            "__info__": {
                "kuid": "afb80803eb8442c7a1a3d1316335c276",
                "srcKUID": "e8ce1f89f6c64e30ba887f3aa0ec320d",
                "wType": "Label"
            }
        },
        "puProfileMenu": {
            "__events__": {},
            "__info__": {
                "isRoot": true,
                "kuid": "a10fca384f254bbe8e771b6fc7229fd7",
                "srcKUID": "h78689376af94e43a801eb4d09759f4e",
                "wType": "FlexContainer"
            },
            "isVisible": false,
            "responsiveData": {
                "b1": {
                    "isVisible": false
                },
                "b3": {
                    "isVisible": false
                }
            }
        },
        "sgmProfileMenu": {
            "__events__": {},
            "__info__": {
                "kuid": "d302eee06d524003ac4bae271a1659bc",
                "srcKUID": "hefb51c8129e4d20be9c41e3c86189d4",
                "wType": "Segment"
            },
            "data": {
                "desktop": [
                    {
                        "btnTransparentButton": {
                            "@class": "com.viz.ide.model.segment.SimpleTextSegmentData",
                            "text": "Button"
                        },
                        "imgArrowRight": {
                            "@class": "com.viz.ide.model.segment.ImageSegmentData",
                            "src": "arrow_right_1.png"
                        },
                        "lblTypeTitle": {
                            "@class": "com.viz.ide.model.segment.SimpleTextSegmentData",
                            "text": "item List"
                        },
                        "lblUILine": {
                            "@class": "com.viz.ide.model.segment.SimpleTextSegmentData",
                            "text": ""
                        }
                    }
                ]
            },
            "responsiveData": {
                "b3": {
                    "isVisible": false
                }
            }
        }
    },
    "desktopweb": {},
    "enablescrolling": true,
    "id": "puProfileMenu",
    "info": null,
    "ipad": {},
    "iphone": {},
    "iscustomlayout": false,
    "isdatareferenced": false,
    "isvisible": true,
    "kiosk": {},
    "kuid": "a10fca384f254bbe8e771b6fc7229fd7",
    "layouttype": 2,
    "masterType": 0,
    "name": "kony.ui.UserWidgetInstance",
    "parent": "frmUploadDocment2",
    "pf": "frmUploadDocment2",
    "responsiveData": {
        "b1": {
            "isVisible": false
        },
        "b3": {
            "isVisible": false
        }
    },
    "retaincontentalignment": false,
    "retainflexpositionproperties": false,
    "snapgridsize": 10,
    "snaptogrid": true,
    "sourceUserWidget": "h78689376af94e43a801eb4d09759f4e",
    "spa": {},
    "spaan": {},
    "spaandroidtablet": {},
    "spabb": {},
    "spaip": {},
    "spaipad": {},
    "spamobile": {},
    "spatablet": {},
    "spawindowstablet": {},
    "spawinphone8": {},
    "tabrcandroid": {},
    "vizProps": {
        "hidewidgethierarchy": false
    },
    "wType": "UserWidgetInstance",
    "windows10": {},
    "windows8": {},
    "winphone10": {},
    "winphone8": {}
}