{
    "DNDConfig": null,
    "__parentReadjusting__": false,
    "_height_": {
        "type": "string",
        "value": "100%"
    },
    "_left_": {
        "type": "string",
        "value": "0dp"
    },
    "_margin_": [
        0,
        0,
        0,
        0
    ],
    "_orientation_": 6,
    "_padding_": [
        0,
        0,
        0,
        0
    ],
    "_percent_": true,
    "_skin_": "sd0e792a4076473c91f13fbdc61bd8dc",
    "_top_": {
        "type": "string",
        "value": "150dp"
    },
    "_width_": {
        "type": "string",
        "value": "100%"
    },
    "allboxes": [],
    "allowhorizontalbounce": false,
    "allowverticalbounce": true,
    "bounces": true,
    "canUpdateUI": true,
    "centerx": {
        "type": "string",
        "value": "50.00%"
    },
    "children": [
        "lblUILine",
        "flxGroupA"
    ],
    "clipbounds": true,
    "containerweight": 100,
    "decelerat": false,
    "dragg": false,
    "enablescrolling": true,
    "horizontalscrollindicator": true,
    "id": "flxContainerHam",
    "info": null,
    "iscustomlayout": false,
    "isvisible": true,
    "kuid": "e0366d9d988c455298661298c0caa5d9",
    "layouttype": 4,
    "name": "kony.ui.FlexScrollContainer",
    "pagingenabled": false,
    "parent": "mainHeaderScreensCopy",
    "pf": "userwidgetmodel",
    "retaincontentalignment": false,
    "retainflexpositionproperties": false,
    "retainflowhorizontalalignment": false,
    "scrolldirection": 2,
    "snapgridsize": 10,
    "snaptogrid": true,
    "track": false,
    "verticalscrollindicator": true,
    "vizProps": {},
    "wType": "FlexScrollContainer",
    "widgetalignment": 1,
    "zindex": 1
}