{
    "DNDConfig": null,
    "__parentReadjusting__": false,
    "_height_": {
        "type": "string",
        "value": "25px"
    },
    "_margin_": [
        0,
        0,
        0,
        0
    ],
    "_orientation_": 6,
    "_padding_": [
        0,
        0,
        0,
        0
    ],
    "_percent_": true,
    "_skin_": "s67b413498f24f68ad2932474874820f",
    "_top_": {
        "type": "string",
        "value": "0px"
    },
    "_width_": {
        "type": "string",
        "value": "100%"
    },
    "allboxes": [],
    "autogrowmode": 0,
    "canUpdateUI": true,
    "centerx": {
        "type": "string",
        "value": "50%"
    },
    "children": [
        "btnPrivacyNoticeMobile",
        "lblLIneMobile1",
        "btnInfoCenterMobile"
    ],
    "clipbounds": true,
    "containerweight": 100,
    "enablescrolling": true,
    "id": "flxContainerFirstLine",
    "info": null,
    "iscustomlayout": false,
    "isvisible": true,
    "kuid": "a51c72478d254dd4a1cdbe9b669c0903",
    "layouttype": 2,
    "name": "kony.ui.FlexContainer",
    "parent": "flxnavIconsContainerMobile",
    "pf": "userwidgetmodel",
    "retaincontentalignment": false,
    "retainflexpositionproperties": false,
    "retainflowhorizontalalignment": false,
    "snapgridsize": 10,
    "snaptogrid": true,
    "wType": "FlexContainer",
    "widgetalignment": 1,
    "zindex": 1
}