{
    "DNDConfig": null,
    "_height_": {
        "type": "string",
        "value": "16px"
    },
    "_left_": {
        "type": "string",
        "value": "1.50%"
    },
    "_margin_": [
        0,
        0,
        0,
        0
    ],
    "_orientation_": 6,
    "_padding_": [
        0,
        0,
        0,
        0
    ],
    "_percent_": true,
    "_skin_": "sc4b3297671f42f19cde385670aab68b",
    "_top_": {
        "type": "string",
        "value": "8px"
    },
    "_width_": {
        "type": "string",
        "value": "38px"
    },
    "allboxes": [],
    "autogrowmode": 0,
    "canUpdateUI": true,
    "children": [
        "lblBadge"
    ],
    "clipbounds": true,
    "containerweight": 100,
    "enablescrolling": true,
    "id": "flxContainerBadge",
    "info": null,
    "iscustomlayout": false,
    "isvisible": true,
    "kuid": "e996badcd80248d29c89898c51fbb85c",
    "layouttype": 2,
    "name": "kony.ui.FlexContainer",
    "parent": "snStateHearingSatusBadge",
    "pf": "userwidgetmodel",
    "retaincontentalignment": false,
    "retainflexpositionproperties": false,
    "snapgridsize": 10,
    "snaptogrid": true,
    "wType": "FlexContainer",
    "widgetalignment": 1,
    "zindex": 2
}