{
    "DNDConfig": null,
    "_height_": {
        "type": "string",
        "value": "220dp"
    },
    "_left_": {
        "type": "string",
        "value": "0dp"
    },
    "_margin_": [
        0,
        0,
        0,
        0
    ],
    "_orientation_": 6,
    "_padding_": [
        0,
        0,
        0,
        0
    ],
    "_percent_": true,
    "_skin_": "s53d4bd2e4c3429fb1031c8fd8a0e190",
    "_top_": {
        "type": "string",
        "value": "0dp"
    },
    "_width_": {
        "type": "string",
        "value": "100%"
    },
    "allboxes": [],
    "canUpdateUI": true,
    "children": [
        "Label0jf255aee0a4e43"
    ],
    "clipbounds": true,
    "containerweight": 100,
    "enablescrolling": true,
    "id": "FlexContainer0e2bcbb59bffc47",
    "info": null,
    "iscustomlayout": false,
    "isvisible": true,
    "kuid": "a2eaea38ef1e477fb2c8d84623fd5f0a",
    "layouttype": 2,
    "name": "kony.ui.FlexContainer",
    "parent": "ResponSive",
    "pf": "ResponSive",
    "responsiveconfig": {
        "offset": {
            "landscape": 0,
            "portrait": 0
        },
        "span": {
            "landscape": 6,
            "portrait": 5
        }
    },
    "retaincontentalignment": false,
    "retainflexpositionproperties": false,
    "retainflowhorizontalalignment": false,
    "snapgridsize": 10,
    "snaptogrid": true,
    "wType": "FlexContainer",
    "widgetalignment": 1,
    "zindex": 1
}