{
    "@class": "com.kony.gen.viz.model.component.KVizLabel",
    "DNDConfig": null,
    "_height_": {
        "type": "ref",
        "value": "preferred"
    },
    "_left_": {
        "type": "string",
        "value": "0dp"
    },
    "_margin_": [
        1,
        1,
        1,
        1
    ],
    "_padding_": [
        0,
        0,
        0,
        0
    ],
    "_skin_": "s1f7f93959b54873987515d05db27025",
    "_text_": "Molly’s Kitchen  | 1LBA/5 LBA",
    "_top_": {
        "type": "string",
        "value": "0dp"
    },
    "_width_": {
        "type": "ref",
        "value": "preferred"
    },
    "_wrapping_": 2,
    "canUpdateUI": true,
    "containerId": true,
    "containerweight": 100,
    "contentalignment": 4,
    "id": "lblProductName",
    "info": null,
    "iscustomlayout": false,
    "isvisible": true,
    "kuid": "ed7d3b6c965d4ddfb6ec7ed9b453a1f0",
    "name": "kony.ui.Label",
    "parent": "flxProductName",
    "pf": "tmpTabCreateOrder",
    "retaincontentalignment": false,
    "retainflexpositionproperties": false,
    "textstyle": {},
    "tooltip": "",
    "wType": "Label",
    "zindex": 1
}