{
    "@class": "com.kony.gen.viz.model.component.KVizLabel",
    "DNDConfig": null,
    "_height_": {
        "type": "ref",
        "value": "preferred"
    },
    "_left_": {
        "type": "string",
        "value": "2%"
    },
    "_margin_": [
        1,
        1,
        1,
        1
    ],
    "_padding_": [
        0,
        0,
        0,
        0
    ],
    "_skin_": "sd475bfd8c944d4fbf0a2ff4732738d5",
    "_text_": "Do you have documents you'd like to provide?",
    "_width_": {
        "type": "string",
        "value": "100%"
    },
    "_wrapping_": 2,
    "android": {
        "textStyle": {
            "letterSpacing": 0,
            "strikeThrough": false
        }
    },
    "canUpdateUI": true,
    "centery": {
        "type": "string",
        "value": "50%"
    },
    "containerweight": 100,
    "contentalignment": 4,
    "id": "lblTextHeaderStep6",
    "info": null,
    "ipad": {
        "psp": {
            "wrapping": 2
        }
    },
    "iphone": {
        "psp": {
            "wrapping": 2
        }
    },
    "iscustomlayout": false,
    "isvisible": true,
    "kuid": "jf421058dad4402a8af2508e31bece6e",
    "name": "kony.ui.Label",
    "parent": "flxContainerHeaderStep6",
    "pf": "frmHearingRequestStep6",
    "responsiveData": {
        "b1": {
            "skin": "s4be6e65a0e44e28a75f2f8d82e29159"
        },
        "b3": {
            "skin": "s83f390e67d14e5b9883382467317f7e"
        }
    },
    "retaincontentalignment": false,
    "retainflexpositionproperties": false,
    "tooltip": "",
    "wType": "Label",
    "zindex": 1
}